LICENSE
MANIFEST.in
README.md
requirements.txt
setup.py
airtest/__init__.py
airtest/__main__.py
airtest/aircv/__init__.py
airtest/aircv/aircv.py
airtest/aircv/cal_confidence.py
airtest/aircv/error.py
airtest/aircv/keypoint_base.py
airtest/aircv/keypoint_matching.py
airtest/aircv/keypoint_matching_contrib.py
airtest/aircv/multiscale_template_matching.py
airtest/aircv/screen_recorder.py
airtest/aircv/sift.py
airtest/aircv/template.py
airtest/aircv/template_matching.py
airtest/aircv/utils.py
airtest/cli/__init__.py
airtest/cli/__main__.py
airtest/cli/info.py
airtest/cli/parser.py
airtest/cli/runner.py
airtest/core/__init__.py
airtest/core/api.py
airtest/core/assertions.py
airtest/core/cv.py
airtest/core/device.py
airtest/core/error.py
airtest/core/helper.py
airtest/core/settings.py
airtest/core/android/__init__.py
airtest/core/android/adb.py
airtest/core/android/android.py
airtest/core/android/constant.py
airtest/core/android/ime.py
airtest/core/android/recorder.py
airtest/core/android/rotation.py
airtest/core/android/yosemite.py
airtest/core/android/cap_methods/__init__.py
airtest/core/android/cap_methods/adbcap.py
airtest/core/android/cap_methods/base_cap.py
airtest/core/android/cap_methods/javacap.py
airtest/core/android/cap_methods/minicap.py
airtest/core/android/cap_methods/screen_proxy.py
airtest/core/android/static/adb/linux/adb
airtest/core/android/static/adb/linux_arm/adb
airtest/core/android/static/adb/mac/adb
airtest/core/android/static/adb/windows/AdbWinApi.dll
airtest/core/android/static/adb/windows/AdbWinUsbApi.dll
airtest/core/android/static/adb/windows/adb.exe
airtest/core/android/static/apks/Yosemite.apk
airtest/core/android/static/apks/maxpresent.jar
airtest/core/android/static/apks/rotationwatcher.jar
airtest/core/android/static/stf_libs/arm64-v8a/minicap
airtest/core/android/static/stf_libs/arm64-v8a/minicap-nopie
airtest/core/android/static/stf_libs/arm64-v8a/minicap.so
airtest/core/android/static/stf_libs/arm64-v8a/minitouch
airtest_sd.egg-info/PKG-INFO
airtest_sd.egg-info/SOURCES.txt
airtest_sd.egg-info/dependency_links.txt
airtest_sd.egg-info/entry_points.txt
airtest_sd.egg-info/requires.txt
airtest_sd.egg-info/top_level.txt