Metadata-Version: 2.1
Name: airtest-sd
Version: 1.0
Summary: UI Test Automation Framework for Games and Apps on Android/iOS/Windows/Linux
Home-page: https://github.com/AirtestProject/Airtest
Author: Netease Games
Author-email: rockywhisper@163.com
License: Apache License 2.0
Keywords: automation,automated-test,game,android,ios,windows,linux
Platform: UNKNOWN
Classifier: Programming Language :: Python :: 3.3
Classifier: Programming Language :: Python :: 3.4
Classifier: Programming Language :: Python :: 3.5
Classifier: Programming Language :: Python :: 3.6
Classifier: Programming Language :: Python :: 3.7
Classifier: Programming Language :: Python :: 3.8
Classifier: Programming Language :: Python :: 3.9
Provides-Extra: tests
Provides-Extra: docs
